pe_tree/__init__.py
pe_tree/__main__.py
pe_tree/carve.py
pe_tree/contextmenu.py
pe_tree/dialogs.py
pe_tree/dump_pe.py
pe_tree/exceptions.py
pe_tree/form.py
pe_tree/ghidra.py
pe_tree/hash_pe.py
pe_tree/info.py
pe_tree/map.py
pe_tree/minidump.py
pe_tree/qstandarditems.py
pe_tree/runtime.py
pe_tree/scandir.py
pe_tree/tree.py
pe_tree/utils.py
pe_tree/volatility.py
pe_tree/window.py
pe_tree/resources/cyberchef.ico
pe_tree/resources/spear.png
pe_tree/resources/virustotal.png
pe_tree-1.0.30.dist-info/LICENSE
pe_tree-1.0.30.dist-info/METADATA
pe_tree-1.0.30.dist-info/WHEEL
pe_tree-1.0.30.dist-info/entry_points.txt
pe_tree-1.0.30.dist-info/top_level.txt
pe_tree-1.0.30.dist-info/RECORD
