Metadata-Version: 2.1
Name: pe-tree
Version: 1.0.30
Summary: View Portable Executable (PE) files in a tree-view using pefile and PyQt5.
Home-page: https://github.com/blackberry/pe_tree
Author: Tom Bonner
Author-email: tbonner@blackberry.com
License: Apache License 2.0
Keywords: pe_tree,petree,pefile,exe,dll,malware,pedump,unpacker,iat,rekall,volatilityminidump
Platform: UNKNOWN
Classifier: Intended Audience :: Developers
Classifier: Intended Audience :: Science/Research
Classifier: Development Status :: 4 - Beta
Classifier: Programming Language :: Python
Classifier: Programming Language :: Python :: 2.7
Classifier: Programming Language :: Python :: 3.5
Classifier: Programming Language :: Python :: 3.6
Classifier: Programming Language :: Python :: 3.7
Classifier: Programming Language :: Python :: 3.8
Classifier: Environment :: X11 Applications :: Qt
Classifier: Environment :: Plugins
Classifier: Operating System :: Microsoft :: Windows
Classifier: Operating System :: MacOS :: MacOS X
Classifier: Operating System :: POSIX :: Linux
Classifier: Topic :: Security
Classifier: Topic :: Utilities
Classifier: Natural Language :: English
Requires-Python: >=2.7
Requires-Dist: pefile
Requires-Dist: requests
Requires-Dist: cryptography
Requires-Dist: configparser
Requires-Dist: asn1crypto
Requires-Dist: scandir
Requires-Dist: filetype
Requires-Dist: minidump
Requires-Dist: pyqt5
Requires-Dist: capstone
